gmlutil_ml_models/feature_engineering.py
gmlutil_ml_models/models.py
gmlutil_ml_models-2.0.4.dist-info/METADATA
gmlutil_ml_models-2.0.4.dist-info/WHEEL
gmlutil_ml_models-2.0.4.dist-info/top_level.txt
gmlutil_ml_models-2.0.4.dist-info/RECORD
