Metadata-Version: 2.1
Name: gmlutil-ml-models
Version: 2.0.4
Summary: General Machine Learning Utility Package for ML Model Training & Testing
Home-page: https://github.com/Phillip1982/gmlutil_ml_models
Author: Phillip Kim
Author-email: phillip.kim@ejgallo.com
License: BSD 2-clause
Classifier: Development Status :: 5 - Production/Stable
Classifier: Framework :: IPython
Classifier: Intended Audience :: Developers
Classifier: License :: OSI Approved :: BSD License
Classifier: Operating System :: MacOS
Classifier: Operating System :: Microsoft :: Windows :: Windows XP
Classifier: Operating System :: POSIX :: Linux
Classifier: Programming Language :: Python :: 3.9
Classifier: Programming Language :: Python :: 3.10
Classifier: Programming Language :: Python :: 3.11
Classifier: Programming Language :: Python :: 3.12
Requires-Dist: numpy (==1.26.4)
Requires-Dist: pandas (<=2.2.2,>2.1.0)
Requires-Dist: imbalanced-learn (>=0.8.0)
Requires-Dist: kmodes (>=0.11.0)
Requires-Dist: packaging (>=21.3)
Requires-Dist: plotly (>=5.5.0)
Requires-Dist: scikit-learn (>=1.3.2)
Requires-Dist: scipy (>=1.5.4)
Requires-Dist: seaborn (>=0.11.2)
Requires-Dist: xgboost (>=1.7.3)
